claudio_requirements_sorter/__init__.py
claudio_requirements_sorter/cli.py
claudio_requirements_sorter/sort_requirements.py
claudio_requirements_sorter-0.6.0.dist-info/LICENSE
claudio_requirements_sorter-0.6.0.dist-info/METADATA
claudio_requirements_sorter-0.6.0.dist-info/WHEEL
claudio_requirements_sorter-0.6.0.dist-info/entry_points.txt
claudio_requirements_sorter-0.6.0.dist-info/top_level.txt
claudio_requirements_sorter-0.6.0.dist-info/RECORD
