Metadata-Version: 2.1
Name: claudio-requirements-sorter
Version: 0.6.0
Summary: Sort requirements file for python 
Home-page: https://github.com/1elie21356/claudio-requirements-sorter
Author: Elie
Author-email: 1elie21356@gmail.com
License: MIT license
Keywords: claudio_requirements_sorter
Platform: UNKNOWN
Classifier: Programming Language :: Python :: 3.6
Requires-Python: >=3.6
Requires-Dist: click (==7.1.2)
